tbase/VERSION.txt
tbase/__init__.py
tbase/run.py
tbase/agents/__init__.py
tbase/agents/a2c_acktr/__init__.py
tbase/agents/a2c_acktr/agent.py
tbase/agents/base/__init__.py
tbase/agents/base/ac_agent.py
tbase/agents/base/base_agent.py
tbase/agents/base/explore.py
tbase/agents/base/multi_agent.py
tbase/agents/ddpg/__init__.py
tbase/agents/ddpg/agent.py
tbase/agents/dummy/__init__.py
tbase/agents/dummy/agent.py
tbase/agents/td3/__init__.py
tbase/agents/td3/agent.py
tbase/common/__init__.py
tbase/common/cmd_util.py
tbase/common/cmd_util_test.py
tbase/common/eval.py
tbase/common/eval_test.py
tbase/common/logger.py
tbase/common/optimizers.py
tbase/common/random_process.py
tbase/common/random_process_test.py
tbase/common/replay_buffer.py
tbase/common/replay_memory.py
tbase/common/torch_utils.py
tbase/common/torch_utils_test.py
tbase/network/__init__.py
tbase/network/base.py
tbase/network/polices.py
tbase/network/polices_test.py
tbase/network/values.py
tbase-0.2.0.dist-info/LICENSE
tbase-0.2.0.dist-info/METADATA
tbase-0.2.0.dist-info/WHEEL
tbase-0.2.0.dist-info/top_level.txt
tbase-0.2.0.dist-info/RECORD
