Metadata-Version: 2.1
Name: tbase
Version: 0.2.0
Summary: 基于强化学习的交易算法Baselines
Home-page: https://github.com/tradingAI/tbase
Author: liuwen
Author-email: liuwen.w@qq.com
License: UNKNOWN
Platform: UNKNOWN
Classifier: Programming Language :: Python :: 3
Classifier: License :: OSI Approved :: MIT License
Classifier: Operating System :: OS Independent
Requires-Python: >=3
Requires-Dist: flake8
Requires-Dist: pytest
Requires-Dist: tenvs
Requires-Dist: torch
Requires-Dist: tensorflow
Requires-Dist: tensorboard
Requires-Dist: trunner
